{
  "version": 2,
  "dependencies": {
    "net8.0": {
      "Avalonia": {
        "type": "Direct",
        "requested": "[11.0.7, )",
        "resolved": "11.0.7",
        "contentHash": "TQYVRzZgv7lWlJzLfIQgAEQpUzhNJr2Bhu609H858FdpzR1x5v1M2N25VxcmbqsvSUKfrCgJRAmfknzPrYG6PQ==",
        "dependencies": {
          "Avalonia.BuildServices": "0.0.29",
          "Avalonia.Remote.Protocol": "11.0.7",
          "MicroCom.Runtime": "0.11.0",
          "System.ComponentModel.Annotations": "4.5.0"
        }
      },
      "Avalonia.Desktop": {
        "type": "Direct",
        "requested": "[11.0.7, )",
        "resolved": "11.0.7",
        "contentHash": "e900dFK7jHJ2WcprLcgJYQoOMc6ejRTwAAMi0VGOFbSczcF98ZDaqwoQIiyqpAwnja59FSbV+GUUXfc3vaQ2Jg==",
        "dependencies": {
          "Avalonia": "11.0.7",
          "Avalonia.Native": "11.0.7",
          "Avalonia.Skia": "11.0.7",
          "Avalonia.Win32": "11.0.7",
          "Avalonia.X11": "11.0.7"
        }
      },
      "Avalonia.Diagnostics": {
        "type": "Direct",
        "requested": "[11.0.7, )",
        "resolved": "11.0.7",
        "contentHash": "Q/45AyITIP50DHUYZZFjGtlZI4GoNkvirybNxwpaNgPkQr8qwG3uvQkM+3IJf8x5wV7zd7mlJUM7UIu7W5QOow==",
        "dependencies": {
          "Avalonia": "11.0.7",
          "Avalonia.Controls.ColorPicker": "11.0.7",
          "Avalonia.Controls.DataGrid": "11.0.7",
          "Avalonia.Themes.Simple": "11.0.7",
          "Microsoft.CodeAnalysis.CSharp.Scripting": "3.8.0",
          "Microsoft.CodeAnalysis.Common": "3.8.0"
        }
      },
      "Avalonia.Skia": {
        "type": "Direct",
        "requested": "[11.0.7, )",
        "resolved": "11.0.7",
        "contentHash": "NkwKPJflsD6SM2xlpCt9HenOAtlOZ4XiBWN4fz7LNJZeNBLmz7qjQhhskHPG5+jwvm5rIfhn6qFmrdLDZ3cOFQ==",
        "dependencies": {
          "Avalonia": "11.0.7",
          "HarfBuzzSharp": "7.3.0",
          "HarfBuzzSharp.NativeAssets.Linux": "7.3.0",
          "HarfBuzzSharp.NativeAssets.WebAssembly": "7.3.0",
          "SkiaSharp": "2.88.7",
          "SkiaSharp.NativeAssets.Linux": "2.88.7",
          "SkiaSharp.NativeAssets.WebAssembly": "2.88.7"
        }
      },
      "Avalonia.Svg.Skia": {
        "type": "Direct",
        "requested": "[11.0.0.12, )",
        "resolved": "11.0.0.12",
        "contentHash": "Rdnmp20yR3R9wxcEU/BqltsR9q8bozmDnE+7GN8KuUT8xXhpPo7HuYajJ52IEIv2jy2naJT6WhdoBgjQzi2rzQ==",
        "dependencies": {
          "Avalonia": "11.0.0",
          "Avalonia.Skia": "11.0.0",
          "SkiaSharp": "2.88.6",
          "Svg.Skia": "1.0.0.12"
        }
      },
      "Avalonia.Xaml.Behaviors": {
        "type": "Direct",
        "requested": "[11.0.6, )",
        "resolved": "11.0.6",
        "contentHash": "4NmtVZuRCMKH9hbLBCM+bzUtU2yz90N7yPuQok4t/sDITmvUEKfLEh3dkPsrliO3eLEZvDZyX/TVyFv2IeuOvg==",
        "dependencies": {
          "Avalonia": "11.0.0",
          "Avalonia.Xaml.Interactions": "11.0.6",
          "Avalonia.Xaml.Interactions.Custom": "11.0.6",
          "Avalonia.Xaml.Interactions.DragAndDrop": "11.0.6",
          "Avalonia.Xaml.Interactions.Draggable": "11.0.6",
          "Avalonia.Xaml.Interactions.Events": "11.0.6",
          "Avalonia.Xaml.Interactions.Reactive": "11.0.6",
          "Avalonia.Xaml.Interactions.Responsive": "11.0.6",
          "Avalonia.Xaml.Interactivity": "11.0.6"
        }
      },
      "Avalonia.Xaml.Interactions": {
        "type": "Direct",
        "requested": "[11.0.6, )",
        "resolved": "11.0.6",
        "contentHash": "4kBQELkjxruQQWyaj2J1QTT3SSrbX/jYzMXvsEX6Aq2b+F2jx5PvUWe4gl+iHSejmjiw+6Z3/XJ4w7hGdCQmDg==",
        "dependencies": {
          "Avalonia": "11.0.0",
          "Avalonia.Xaml.Interactivity": "11.0.6"
        }
      },
      "Avalonia.Xaml.Interactivity": {
        "type": "Direct",
        "requested": "[11.0.6, )",
        "resolved": "11.0.6",
        "contentHash": "VoDOCs7mJxrP61p7TuX+JV/DWJ4hdlV+ezTLEsxRV2/4szvRw5f2wtXyYQzjDfDw3Cut5sBM1Y4bhu2xg7A7aQ==",
        "dependencies": {
          "Avalonia": "11.0.0"
        }
      },
      "CommandLineParser": {
        "type": "Direct",
        "requested": "[2.9.1, )",
        "resolved": "2.9.1",
        "contentHash": "OE0sl1/sQ37bjVsPKKtwQlWDgqaxWgtme3xZz7JssWUzg5JpMIyHgCTY9MVMxOg48fJ1AgGT3tgdH5m/kQ5xhA=="
      },
      "FluentAvaloniaUI": {
        "type": "Direct",
        "requested": "[2.0.4, )",
        "resolved": "2.0.4",
        "contentHash": "bFw0B4RJUuOba2FPOz4VIcj8CpFgkxTQCBWbMFYvY0zU9w4nrhnDptC8oSLZcFRTm7Wd5oaFgNexnrHhicC0Mg==",
        "dependencies": {
          "Avalonia": "11.0.4",
          "Avalonia.Controls.ColorPicker": "11.0.4",
          "Avalonia.Controls.DataGrid": "11.0.4",
          "Avalonia.Controls.ItemsRepeater": "11.0.4",
          "Avalonia.Skia": "11.0.4",
          "MicroCom.CodeGenerator.MSBuild": "0.11.0",
          "MicroCom.Runtime": "0.11.0"
        }
      },
      "Generator.Equals": {
        "type": "Direct",
        "requested": "[2.2.3, )",
        "resolved": "2.2.3",
        "contentHash": "Fsxq1NicJ3QLO+66Psbid2Bpo7lxRVO5RqYQ+y+umHODLY1a22hbjLR8vv7LzNUz+y7fZ1G6y31XHbhaUcrgmQ==",
        "dependencies": {
          "Generator.Equals.Runtime": "2.2.3"
        }
      },
      "GitInfo": {
        "type": "Direct",
        "requested": "[2.2.0, )",
        "resolved": "2.2.0",
        "contentHash": "SKTmjt40sYqoDB3S7HFVUToUN/vl6Zrt+PuSHdjbQDlcBx0JAZBdS7BXVbVKyy+0iaaF3FBd4ZxspIlKQCC9Lw=="
      },
      "Microsoft.Extensions.DependencyInjection": {
        "type": "Direct",
        "requested": "[6.0.0, )",
        "resolved": "6.0.0",
        "contentHash": "k6PWQMuoBDGGHOQTtyois2u4AwyVcIwL2LaSLlTZQm2CYcJ1pxbt6jfAnpWmzENA/wfrYRI/X9DTLoUkE4AsLw==",
        "dependencies": {
          "Microsoft.Extensions.DependencyInjection.Abstractions": "6.0.0",
          "System.Runtime.CompilerServices.Unsafe": "6.0.0"
        }
      },
      "Microsoft.NET.ILLink.Tasks": {
        "type": "Direct",
        "requested": "[8.0.1, )",
        "resolved": "8.0.1",
        "contentHash": "ADdJXuKNjwZDfBmybMnpvwd5CK3gp92WkWqqeQhW4W+q4MO3Qaa9QyW2DcFLAvCDMcCWxT5hRXqGdv13oon7nA=="
      },
      "NLog": {
        "type": "Direct",
        "requested": "[5.2.7, )",
        "resolved": "5.2.7",
        "contentHash": "Ww/0b6V1NL8iqpFKtRKVQFFX03LoowNzYeNG6FpVzmhgCfLAkW0h/4lT3+V8mHfyvtHptNoV8Cz0YePLFRUaPA=="
      },
      "ReactiveProperty": {
        "type": "Direct",
        "requested": "[8.0.3, )",
        "resolved": "8.0.3",
        "contentHash": "+1cDRNtO9p9K7OBzcJezZauzpdwQ/yStggDjUdDD9XfIC7/6D8iRTX5Qz12/PrG/r8xNLmwvQBATuObDkPySsA==",
        "dependencies": {
          "ReactiveProperty.Core": "8.0.3",
          "System.ComponentModel.Annotations": "5.0.0",
          "System.Reactive": "5.0.0"
        }
      },
      "System.Text.Json": {
        "type": "Direct",
        "requested": "[7.0.1, )",
        "resolved": "7.0.1",
        "contentHash": "OtDEmCCiNl8JAduFKZ/r0Sw6XZNHwIicUYy/mXgMDGeOsZLshH37qi3oPRzFYiryVktiMoQLByMGPtRCEMYbeQ==",
        "dependencies": {
          "System.Text.Encodings.Web": "7.0.0"
        }
      },
      "YamlDotNet": {
        "type": "Direct",
        "requested": "[11.2.1, )",
        "resolved": "11.2.1",
        "contentHash": "tBt8K+korVfrjH9wyDEhiLKxbs8qoLCLIFwvYgkSUuMC9//w3z0cFQ8LQAI/5MCKq+BMil0cfRTRvPeE7eXhQw=="
      },
      "Avalonia.Angle.Windows.Natives": {
        "type": "Transitive",
        "resolved": "2.1.0.2023020321",
        "contentHash": "Zlkkb8ipxrxNWVPCJgMO19fpcpYPP+bpOQ+jPtCFj8v+TzVvPdnGHuyv9IMvSHhhMfEpps4m4hjaP4FORQYVAA=="
      },
      "Avalonia.BuildServices": {
        "type": "Transitive",
        "resolved": "0.0.29",
        "contentHash": "U4eJLQdoDNHXtEba7MZUCwrBErBTxFp6sUewXBOdAhU0Kwzwaa/EKFcYm8kpcysjzKtfB4S0S9n0uxKZFz/ikw=="
      },
      "Avalonia.Controls.ColorPicker": {
        "type": "Transitive",
        "resolved": "11.0.7",
        "contentHash": "KeISitlmFxjE+LxfD/DIVvgQlPDRQOzpvGeXX8/7vkcjgoHPzWK09+F+8JLw1Kl897mPv2mYRIN8rcTAtCFy+w==",
        "dependencies": {
          "Avalonia": "11.0.7",
          "Avalonia.Remote.Protocol": "11.0.7"
        }
      },
      "Avalonia.Controls.ItemsRepeater": {
        "type": "Transitive",
        "resolved": "11.0.4",
        "contentHash": "wpohui8M3BHskyfZuyF1GorDyL4K/ShWBRvi1V2iH7Vj/YqgWTqGtxi8YEmlbOm9SG+hw8bblGAjmk0WvB4o2w==",
        "dependencies": {
          "Avalonia": "11.0.4"
        }
      },
      "Avalonia.FreeDesktop": {
        "type": "Transitive",
        "resolved": "11.0.7",
        "contentHash": "Mg6amM2ZBV8O8khrNLGvwihX5Ajy5NIOrIBZTOiJ3fg3Y9cp2wkpp55KEK7ibvidsiLQ5PqqKtZHST2Q9g92RQ==",
        "dependencies": {
          "Avalonia": "11.0.7",
          "Tmds.DBus.Protocol": "0.15.0"
        }
      },
      "Avalonia.Native": {
        "type": "Transitive",
        "resolved": "11.0.7",
        "contentHash": "STdM/t3phThu+kigdoPLrivVDyYxc7lxpIwjlptzZ/0PhMxno/tKqDklatu/g4au9r+NsfQJEHctghLL1dvrSQ==",
        "dependencies": {
          "Avalonia": "11.0.7"
        }
      },
      "Avalonia.Remote.Protocol": {
        "type": "Transitive",
        "resolved": "11.0.7",
        "contentHash": "eKfTDTgLoz8LFdL7pwCPrHVbqFqZ6i7JJn3I1gqjLueXEwLTrgG10ui3znUbkJNkk/9cz77ORxbCBQrwn7n4wA=="
      },
      "Avalonia.Themes.Simple": {
        "type": "Transitive",
        "resolved": "11.0.7",
        "contentHash": "6KsPmlOvbrOobBsbvJ2g/VWu3UQIX1iAO4e8iypM1WjOed81rUB5Wt+7EohdhAWNX8WuYl91NeBZOGxu4SOINw==",
        "dependencies": {
          "Avalonia": "11.0.7"
        }
      },
      "Avalonia.Win32": {
        "type": "Transitive",
        "resolved": "11.0.7",
        "contentHash": "epEcY6/Tbg0I+QZIL2xqLZMC2xz7XDhsZJhmERQeHn8cJ1EGN/a3m0f8AYNK+rmw9No5fQsGFx++vxioUKb/Jg==",
        "dependencies": {
          "Avalonia": "11.0.7",
          "Avalonia.Angle.Windows.Natives": "2.1.0.2023020321",
          "System.Drawing.Common": "6.0.0",
          "System.Numerics.Vectors": "4.5.0"
        }
      },
      "Avalonia.X11": {
        "type": "Transitive",
        "resolved": "11.0.7",
        "contentHash": "8yTTBK4dYDi4jndjX3hrfhKd9qtKeMOjsFZ+fvM5McllNbx0ZX/lV5ROrMZcvq89pBAsp0njGm1MilXqaY/xqg==",
        "dependencies": {
          "Avalonia": "11.0.7",
          "Avalonia.FreeDesktop": "11.0.7",
          "Avalonia.Skia": "11.0.7"
        }
      },
      "Avalonia.Xaml.Interactions.Custom": {
        "type": "Transitive",
        "resolved": "11.0.6",
        "contentHash": "BCGfsRWfwMNyAvZt6xJmTg/JIu9nGv4UkniF9w2c1qI1bTJP9sTdr+/o3+odBCcMUvWdm9MQ/tkrpI3AIgDcJw==",
        "dependencies": {
          "Avalonia": "11.0.0",
          "Avalonia.Xaml.Interactivity": "11.0.6"
        }
      },
      "Avalonia.Xaml.Interactions.DragAndDrop": {
        "type": "Transitive",
        "resolved": "11.0.6",
        "contentHash": "jTmi5TEawJBRADTl/lgkEspFRsvKYPdEfSicny61AfW29+0dWMqmQDJLx7u2Xlet2s3X6SgPNTILY79EXvDKqg==",
        "dependencies": {
          "Avalonia": "11.0.0",
          "Avalonia.Xaml.Interactivity": "11.0.6"
        }
      },
      "Avalonia.Xaml.Interactions.Draggable": {
        "type": "Transitive",
        "resolved": "11.0.6",
        "contentHash": "+AzZlo5EYAsVEXny3tGYXOmPdwkCIEB55mEemQpM9DoAnU6lZsPAXET3TpU3LObiTaG3Ju1vPCq/wgFnA/cw3A==",
        "dependencies": {
          "Avalonia": "11.0.0",
          "Avalonia.Xaml.Interactivity": "11.0.6"
        }
      },
      "Avalonia.Xaml.Interactions.Events": {
        "type": "Transitive",
        "resolved": "11.0.6",
        "contentHash": "/v+IbRyaOl/FcepPvgqcwtfph6/hITsZGbcsV6s8eoe3Z/WY6wBkIeGhFmttqJAu0Yv1YPTO8vyYS43t8cPoxA==",
        "dependencies": {
          "Avalonia": "11.0.0",
          "Avalonia.Xaml.Interactivity": "11.0.6"
        }
      },
      "Avalonia.Xaml.Interactions.Reactive": {
        "type": "Transitive",
        "resolved": "11.0.6",
        "contentHash": "UGPpJkdh5Y73ClxGJrC9NAAZWIEItuWwio7HkMiaU8bBdIaLXFpd0pJkRYAzTfFr8OeAeHZOlE97cWe8IM4FQg==",
        "dependencies": {
          "Avalonia": "11.0.0",
          "Avalonia.Xaml.Interactivity": "11.0.6",
          "System.Reactive": "5.0.0"
        }
      },
      "Avalonia.Xaml.Interactions.Responsive": {
        "type": "Transitive",
        "resolved": "11.0.6",
        "contentHash": "8JfEeeQqyK4xUR93kfZQL5stdpMFCNTy0G99Bg7gg3Js0eGNne2bkVUWb3CXz9XuLkdRl7WGQlRYr4HIOTpfWg==",
        "dependencies": {
          "Avalonia": "11.0.0",
          "Avalonia.Xaml.Interactivity": "11.0.6"
        }
      },
      "ExCSS": {
        "type": "Transitive",
        "resolved": "4.2.3",
        "contentHash": "SyeAfu2wL5247sipJoPUzQfjiwQtfSd8hN4IbgoyVcDx4PP6Dud4znwPRibWQzLtTlUxYYcbf5f4p+EfFC7KtQ=="
      },
      "Generator.Equals.Runtime": {
        "type": "Transitive",
        "resolved": "2.2.3",
        "contentHash": "1xtv5wndUdN4jv79zDF5WvDoWOFxKPxM2sM+r90W2BVycoCB65ZvBqOrDyneIzxmwB7QAAcmXLv3MfWUGIUjxg==",
        "dependencies": {
          "Microsoft.Bcl.HashCode": "1.1.0"
        }
      },
      "HarfBuzzSharp": {
        "type": "Transitive",
        "resolved": "7.3.0",
        "contentHash": "OrQLaxtZMIeS2yHSUtsKzeSdk9CPaCpyJ/JCs+wLfRGatjE8MLUS6LGj6vdbGRxqRavcXs79C9O3oWe6FJR0JQ==",
        "dependencies": {
          "HarfBuzzSharp.NativeAssets.Win32": "7.3.0",
          "HarfBuzzSharp.NativeAssets.macOS": "7.3.0"
        }
      },
      "HarfBuzzSharp.NativeAssets.Linux": {
        "type": "Transitive",
        "resolved": "7.3.0",
        "contentHash": "m6F2pEBTN0zTRgQ3caJQRGQkZZizZwHHCbu+rTv+gvwteNBOpqOLD5GE4dB9TFjNNpnyHXtfuMD86JuUra9UvA==",
        "dependencies": {
          "HarfBuzzSharp": "7.3.0"
        }
      },
      "HarfBuzzSharp.NativeAssets.macOS": {
        "type": "Transitive",
        "resolved": "7.3.0",
        "contentHash": "LWcFJ39j+dN0KK8c/GJJZPPZPL9TqT2FA42/LRGqzUMmSm5LYbINOMnPvUr7RuLR6RFSmKIrgrlgObR8G5ho2A=="
      },
      "HarfBuzzSharp.NativeAssets.WebAssembly": {
        "type": "Transitive",
        "resolved": "7.3.0",
        "contentHash": "cnl4I6P+VeujfSSD3ZrC5f0TrTGt9EKgCOoZ3LpgLI2xobBKLi5bxOaN2oY6B0xVXxQEhEaWBotg7AuECg00Iw=="
      },
      "HarfBuzzSharp.NativeAssets.Win32": {
        "type": "Transitive",
        "resolved": "7.3.0",
        "contentHash": "ulEewLMk+dNmbmpy15ny/YusI6JNUWqchF080TV2jgfFBXPXjWm767JleDi/S7hp8eDeEN6GYIIxpvNr5fLvIw=="
      },
      "MicroCom.CodeGenerator.MSBuild": {
        "type": "Transitive",
        "resolved": "0.11.0",
        "contentHash": "CiRuIIvycn7RqT7p72+JdJsw1/No/1nc0Vs45Qkbvkn/uryWU57dGAUaqy9p2trRDvbsRBdQgF1hWLNUpgUSQw=="
      },
      "MicroCom.Runtime": {
        "type": "Transitive",
        "resolved": "0.11.0",
        "contentHash": "MEnrZ3UIiH40hjzMDsxrTyi8dtqB5ziv3iBeeU4bXsL/7NLSal9F1lZKpK+tfBRnUoDSdtcW3KufE4yhATOMCA=="
      },
      "Microsoft.Bcl.HashCode": {
        "type": "Transitive",
        "resolved": "1.1.0",
        "contentHash": "J2G1k+u5unBV+aYcwxo94ip16Rkp65pgWFb0R6zwJipzWNMgvqlWeuI7/+R+e8bob66LnSG+llLJ+z8wI94cHg=="
      },
      "Microsoft.CodeAnalysis.Analyzers": {
        "type": "Transitive",
        "resolved": "3.0.0",
        "contentHash": "ojG5pGAhTPmjxRGTNvuszO3H8XPZqksDwr9xLd4Ae/JBjZZdl6GuoLk7uLMf+o7yl5wO0TAqoWcEKkEWqrZE5g=="
      },
      "Microsoft.CodeAnalysis.Common": {
        "type": "Transitive",
        "resolved": "3.8.0",
        "contentHash": "8YTZ7GpsbTdC08DITx7/kwV0k4SC6cbBAFqc13cOm5vKJZcEIAh51tNSyGSkWisMgYCr96B2wb5Zri1bsla3+g==",
        "dependencies": {
          "Microsoft.CodeAnalysis.Analyzers": "3.0.0",
          "System.Collections.Immutable": "5.0.0",
          "System.Memory": "4.5.4",
          "System.Reflection.Metadata": "5.0.0",
          "System.Runtime.CompilerServices.Unsafe": "4.7.1",
          "System.Text.Encoding.CodePages": "4.5.1",
          "System.Threading.Tasks.Extensions": "4.5.4"
        }
      },
      "Microsoft.CodeAnalysis.CSharp": {
        "type": "Transitive",
        "resolved": "3.8.0",
        "contentHash": "hKqFCUSk9TIMBDjiYMF8/ZfK9p9mzpU+slM73CaCHu4ctfkoqJGHLQhyT8wvrYsIg+ufrUWBF8hcJYmyr5rc5Q==",
        "dependencies": {
          "Microsoft.CodeAnalysis.Common": "[3.8.0]"
        }
      },
      "Microsoft.CodeAnalysis.CSharp.Scripting": {
        "type": "Transitive",
        "resolved": "3.8.0",
        "contentHash": "+XVKzByNigzzvl7rGwpzFrkUbbekNUwdMW3EghcxmNRZd9aamNXxes3I/U0tYx1LTeHEQ5y/nzb7SiEmXBmzEA==",
        "dependencies": {
          "Microsoft.CSharp": "4.3.0",
          "Microsoft.CodeAnalysis.CSharp": "[3.8.0]",
          "Microsoft.CodeAnalysis.Common": "[3.8.0]",
          "Microsoft.CodeAnalysis.Scripting.Common": "[3.8.0]"
        }
      },
      "Microsoft.CodeAnalysis.Scripting.Common": {
        "type": "Transitive",
        "resolved": "3.8.0",
        "contentHash": "lR8Mxg/4tnwzFyqJOD7wBoXbyDKEaMxRc0E9UWtHNGBiL1qBdYyVhXPmiOPUL44tUJeQwCOHAr554jRHGBQIcw==",
        "dependencies": {
          "Microsoft.CodeAnalysis.Common": "[3.8.0]"
        }
      },
      "Microsoft.CSharp": {
        "type": "Transitive",
        "resolved": "4.3.0",
        "contentHash": "P+MBhIM0YX+JqROuf7i306ZLJEjQYA9uUyRDE+OqwUI5sh41e2ZbPQV3LfAPh+29cmceE1pUffXsGfR4eMY3KA==",
        "dependencies": {
          "System.Collections": "4.3.0",
          "System.Diagnostics.Debug": "4.3.0",
          "System.Dynamic.Runtime": "4.3.0",
          "System.Globalization": "4.3.0",
          "System.Linq": "4.3.0",
          "System.Linq.Expressions": "4.3.0",
          "System.ObjectModel": "4.3.0",
          "System.Reflection": "4.3.0",
          "System.Reflection.Extensions": "4.3.0",
          "System.Reflection.Primitives": "4.3.0",
          "System.Reflection.TypeExtensions": "4.3.0",
          "System.Resources.ResourceManager": "4.3.0",
          "System.Runtime": "4.3.0",
          "System.Runtime.Extensions": "4.3.0",
          "System.Runtime.InteropServices": "4.3.0",
          "System.Threading": "4.3.0"
        }
      },
      "Microsoft.Extensions.DependencyInjection.Abstractions": {
        "type": "Transitive",
        "resolved": "6.0.0",
        "contentHash": "xlzi2IYREJH3/m6+lUrQlujzX8wDitm4QGnUu6kUXTQAWPuZY8i+ticFJbzfqaetLA6KR/rO6Ew/HuYD+bxifg=="
      },
      "Microsoft.NETCore.Platforms": {
        "type": "Transitive",
        "resolved": "2.1.2",
        "contentHash": "mOJy3M0UN+LUG21dLGMxaWZEP6xYpQEpLuvuEQBaownaX4YuhH6NmNUlN9si+vNkAS6dwJ//N1O4DmLf2CikVg=="
      },
      "Microsoft.NETCore.Targets": {
        "type": "Transitive",
        "resolved": "1.1.0",
        "contentHash": "aOZA3BWfz9RXjpzt0sRJJMjAscAUm3Hoa4UWAfceV9UTYxgwZ1lZt5nO2myFf+/jetYQo4uTP7zS8sJY67BBxg=="
      },
      "Microsoft.Win32.SystemEvents": {
        "type": "Transitive",
        "resolved": "6.0.0",
        "contentHash": "hqTM5628jSsQiv+HGpiq3WKBl2c8v1KZfby2J6Pr7pEPlK9waPdgEO6b8A/+/xn/yZ9ulv8HuqK71ONy2tg67A=="
      },
      "ReactiveProperty.Core": {
        "type": "Transitive",
        "resolved": "8.0.3",
        "contentHash": "f+KnptDVfhaAgWgwvx6ywnsht/JDH5TQfXFfd6ugCQHnR0OEWjjEgwp9EzqUmrkHFvu01fbKRDeJ85xdDgVs4w=="
      },
      "ShimSkiaSharp": {
        "type": "Transitive",
        "resolved": "1.0.0.12",
        "contentHash": "qXsZ7gABPFHMTJ902mwPhGMiAQAMJnyOs5EXeLiOMlLFQIt0aLM6rreD0Fj6Nm8GQzAj8kb0JwxeAjmGSD91FQ=="
      },
      "SkiaSharp": {
        "type": "Transitive",
        "resolved": "2.88.7",
        "contentHash": "LJHAMrbWO00J7jXWLWehyjqFo29T4VzABimfJb4nICqpEe3c/KvQGWL4ItON8ymzhxYOeFgyxeRzuNzO4GHSug==",
        "dependencies": {
          "SkiaSharp.NativeAssets.Win32": "2.88.7",
          "SkiaSharp.NativeAssets.macOS": "2.88.7"
        }
      },
      "SkiaSharp.HarfBuzz": {
        "type": "Transitive",
        "resolved": "2.88.6",
        "contentHash": "s5yZTHdqbXKiTL06ns6zW3asELfX60dEceA4ZdYmNlOkz/OyWDfdjHAuu4HGDA7Mxx5iaUEzDZgPkEe+OVr/jg==",
        "dependencies": {
          "HarfBuzzSharp": "7.3.0",
          "SkiaSharp": "2.88.6"
        }
      },
      "SkiaSharp.NativeAssets.Linux": {
        "type": "Transitive",
        "resolved": "2.88.7",
        "contentHash": "i9VitS7/5D8Te3B1Gu7F6kakW9PYVnI3YC6MoR6NidreD9hDl1EIOQEBaa0eBsOsWNX5Bz92OVf6+7KbDrJvyg==",
        "dependencies": {
          "SkiaSharp": "2.88.7"
        }
      },
      "SkiaSharp.NativeAssets.macOS": {
        "type": "Transitive",
        "resolved": "2.88.7",
        "contentHash": "3jNzco4VjcYPFNxR9aNWcgweFXbTSdM1VpNRzCS4X0i1A1OuNqcaulrAvmntNpujeWxHo9e6WGh6FN8Jf5+XhA=="
      },
      "SkiaSharp.NativeAssets.WebAssembly": {
        "type": "Transitive",
        "resolved": "2.88.7",
        "contentHash": "elmOOQTO0QXmnnHx7GliF7VNJqZkWgPqqPsXapEN0EEZJ9fGblYWmD6cqxTwaRTMCUFeLpn8+gTzY8j000MxZQ=="
      },
      "SkiaSharp.NativeAssets.Win32": {
        "type": "Transitive",
        "resolved": "2.88.7",
        "contentHash": "BCXmWdQ0oVck9vRwC8U3ocSaTHEx28VB+6qw9OxGIMQ86iO5bp4Flqk3IXH0l9Pbr7vWAUOpI212iaL9mTaUZQ=="
      },
      "Svg.Custom": {
        "type": "Transitive",
        "resolved": "1.0.0.12",
        "contentHash": "sf5QG6cTwdSgcjZY8Id85s+w5CDArJPdhh2GeDZL+26RKprkP1IfERUlZIkQcO/f7W2iDMMuq/8Wwqmg00xshw==",
        "dependencies": {
          "ExCSS": "4.2.3"
        }
      },
      "Svg.Model": {
        "type": "Transitive",
        "resolved": "1.0.0.12",
        "contentHash": "oAKJXPrZ5xtpO3vZBNBWxIK+7HzNzmqs9Vgg/HsrRGxBgw7VOQ6jOgdD8wPbg2CEGio0W/uwnOFTnSGDl9g0Og==",
        "dependencies": {
          "ShimSkiaSharp": "1.0.0.12",
          "Svg.Custom": "1.0.0.12"
        }
      },
      "Svg.Skia": {
        "type": "Transitive",
        "resolved": "1.0.0.12",
        "contentHash": "OX3x/AqINkcrNo3iFbyimVV6UO2GDV33eD1Mu4FYDXI60tpiug5ZZtq6xPPkIaBdQNNq672PcSQAcuqE/tl9TQ==",
        "dependencies": {
          "SkiaSharp": "2.88.6",
          "SkiaSharp.HarfBuzz": "2.88.6",
          "Svg.Custom": "1.0.0.12",
          "Svg.Model": "1.0.0.12"
        }
      },
      "System.Collections": {
        "type": "Transitive",
        "resolved": "4.3.0",
        "contentHash": "3Dcj85/TBdVpL5Zr+gEEBUuFe2icOnLalmEh9hfck1PTYbbyWuZgh4fmm2ysCLTrqLQw6t3TgTyJ+VLp+Qb+Lw==",
        "dependencies": {
          "Microsoft.NETCore.Platforms": "1.1.0",
          "Microsoft.NETCore.Targets": "1.1.0",
          "System.Runtime": "4.3.0"
        }
      },
      "System.Collections.Immutable": {
        "type": "Transitive",
        "resolved": "5.0.0",
        "contentHash": "FXkLXiK0sVVewcso0imKQoOxjoPAj42R8HtjjbSjVPAzwDfzoyoznWxgA3c38LDbN9SJux1xXoXYAhz98j7r2g=="
      },
      "System.ComponentModel.Annotations": {
        "type": "Transitive",
        "resolved": "5.0.0",
        "contentHash": "dMkqfy2el8A8/I76n2Hi1oBFEbG1SfxD2l5nhwXV3XjlnOmwxJlQbYpJH4W51odnU9sARCSAgv7S3CyAFMkpYg=="
      },
      "System.Diagnostics.Debug": {
        "type": "Transitive",
        "resolved": "4.3.0",
        "contentHash": "ZUhUOdqmaG5Jk3Xdb8xi5kIyQYAA4PnTNlHx1mu9ZY3qv4ELIdKbnL/akbGaKi2RnNUWaZsAs31rvzFdewTj2g==",
        "dependencies": {
          "Microsoft.NETCore.Platforms": "1.1.0",
          "Microsoft.NETCore.Targets": "1.1.0",
          "System.Runtime": "4.3.0"
        }
      },
      "System.Drawing.Common": {
        "type": "Transitive",
        "resolved": "6.0.0",
        "contentHash": "NfuoKUiP2nUWwKZN6twGqXioIe1zVD0RIj2t976A+czLHr2nY454RwwXs6JU9Htc6mwqL6Dn/nEL3dpVf2jOhg==",
        "dependencies": {
          "Microsoft.Win32.SystemEvents": "6.0.0"
        }
      },
      "System.Dynamic.Runtime": {
        "type": "Transitive",
        "resolved": "4.3.0",
        "contentHash": "SNVi1E/vfWUAs/WYKhE9+qlS6KqK0YVhnlT0HQtr8pMIA8YX3lwy3uPMownDwdYISBdmAF/2holEIldVp85Wag==",
        "dependencies": {
          "System.Collections": "4.3.0",
          "System.Diagnostics.Debug": "4.3.0",
          "System.Linq": "4.3.0",
          "System.Linq.Expressions": "4.3.0",
          "System.ObjectModel": "4.3.0",
          "System.Reflection": "4.3.0",
          "System.Reflection.Emit": "4.3.0",
          "System.Reflection.Emit.ILGeneration": "4.3.0",
          "System.Reflection.Primitives": "4.3.0",
          "System.Reflection.TypeExtensions": "4.3.0",
          "System.Resources.ResourceManager": "4.3.0",
          "System.Runtime": "4.3.0",
          "System.Runtime.Extensions": "4.3.0",
          "System.Threading": "4.3.0"
        }
      },
      "System.Globalization": {
        "type": "Transitive",
        "resolved": "4.3.0",
        "contentHash": "kYdVd2f2PAdFGblzFswE4hkNANJBKRmsfa2X5LG2AcWE1c7/4t0pYae1L8vfZ5xvE2nK/R9JprtToA61OSHWIg==",
        "dependencies": {
          "Microsoft.NETCore.Platforms": "1.1.0",
          "Microsoft.NETCore.Targets": "1.1.0",
          "System.Runtime": "4.3.0"
        }
      },
      "System.IO": {
        "type": "Transitive",
        "resolved": "4.3.0",
        "contentHash": "3qjaHvxQPDpSOYICjUoTsmoq5u6QJAFRUITgeT/4gqkF1bajbSmb1kwSxEA8AHlofqgcKJcM8udgieRNhaJ5Cg==",
        "dependencies": {
          "Microsoft.NETCore.Platforms": "1.1.0",
          "Microsoft.NETCore.Targets": "1.1.0",
          "System.Runtime": "4.3.0",
          "System.Text.Encoding": "4.3.0",
          "System.Threading.Tasks": "4.3.0"
        }
      },
      "System.Linq": {
        "type": "Transitive",
        "resolved": "4.3.0",
        "contentHash": "5DbqIUpsDp0dFftytzuMmc0oeMdQwjcP/EWxsksIz/w1TcFRkZ3yKKz0PqiYFMmEwPSWw+qNVqD7PJ889JzHbw==",
        "dependencies": {
          "System.Collections": "4.3.0",
          "System.Diagnostics.Debug": "4.3.0",
          "System.Resources.ResourceManager": "4.3.0",
          "System.Runtime": "4.3.0",
          "System.Runtime.Extensions": "4.3.0"
        }
      },
      "System.Linq.Expressions": {
        "type": "Transitive",
        "resolved": "4.3.0",
        "contentHash": "PGKkrd2khG4CnlyJwxwwaWWiSiWFNBGlgXvJpeO0xCXrZ89ODrQ6tjEWS/kOqZ8GwEOUATtKtzp1eRgmYNfclg==",
        "dependencies": {
          "System.Collections": "4.3.0",
          "System.Diagnostics.Debug": "4.3.0",
          "System.Globalization": "4.3.0",
          "System.IO": "4.3.0",
          "System.Linq": "4.3.0",
          "System.ObjectModel": "4.3.0",
          "System.Reflection": "4.3.0",
          "System.Reflection.Emit": "4.3.0",
          "System.Reflection.Emit.ILGeneration": "4.3.0",
          "System.Reflection.Emit.Lightweight": "4.3.0",
          "System.Reflection.Extensions": "4.3.0",
          "System.Reflection.Primitives": "4.3.0",
          "System.Reflection.TypeExtensions": "4.3.0",
          "System.Resources.ResourceManager": "4.3.0",
          "System.Runtime": "4.3.0",
          "System.Runtime.Extensions": "4.3.0",
          "System.Threading": "4.3.0"
        }
      },
      "System.Memory": {
        "type": "Transitive",
        "resolved": "4.5.4",
        "contentHash": "1MbJTHS1lZ4bS4FmsJjnuGJOu88ZzTT2rLvrhW7Ygic+pC0NWA+3hgAen0HRdsocuQXCkUTdFn9yHJJhsijDXw=="
      },
      "System.Numerics.Vectors": {
        "type": "Transitive",
        "resolved": "4.5.0",
        "contentHash": "QQTlPTl06J/iiDbJCiepZ4H//BVraReU4O4EoRw1U02H5TLUIT7xn3GnDp9AXPSlJUDyFs4uWjWafNX6WrAojQ=="
      },
      "System.ObjectModel": {
        "type": "Transitive",
        "resolved": "4.3.0",
        "contentHash": "bdX+80eKv9bN6K4N+d77OankKHGn6CH711a6fcOpMQu2Fckp/Ft4L/kW9WznHpyR0NRAvJutzOMHNNlBGvxQzQ==",
        "dependencies": {
          "System.Collections": "4.3.0",
          "System.Diagnostics.Debug": "4.3.0",
          "System.Resources.ResourceManager": "4.3.0",
          "System.Runtime": "4.3.0",
          "System.Threading": "4.3.0"
        }
      },
      "System.Reactive": {
        "type": "Transitive",
        "resolved": "5.0.0",
        "contentHash": "erBZjkQHWL9jpasCE/0qKAryzVBJFxGHVBAvgRN1bzM0q2s1S4oYREEEL0Vb+1kA/6BKb5FjUZMp5VXmy+gzkQ=="
      },
      "System.Reflection": {
        "type": "Transitive",
        "resolved": "4.3.0",
        "contentHash": "KMiAFoW7MfJGa9nDFNcfu+FpEdiHpWgTcS2HdMpDvt9saK3y/G4GwprPyzqjFH9NTaGPQeWNHU+iDlDILj96aQ==",
        "dependencies": {
          "Microsoft.NETCore.Platforms": "1.1.0",
          "Microsoft.NETCore.Targets": "1.1.0",
          "System.IO": "4.3.0",
          "System.Reflection.Primitives": "4.3.0",
          "System.Runtime": "4.3.0"
        }
      },
      "System.Reflection.Emit": {
        "type": "Transitive",
        "resolved": "4.3.0",
        "contentHash": "228FG0jLcIwTVJyz8CLFKueVqQK36ANazUManGaJHkO0icjiIypKW7YLWLIWahyIkdh5M7mV2dJepllLyA1SKg==",
        "dependencies": {
          "System.IO": "4.3.0",
          "System.Reflection": "4.3.0",
          "System.Reflection.Emit.ILGeneration": "4.3.0",
          "System.Reflection.Primitives": "4.3.0",
          "System.Runtime": "4.3.0"
        }
      },
      "System.Reflection.Emit.ILGeneration": {
        "type": "Transitive",
        "resolved": "4.3.0",
        "contentHash": "59tBslAk9733NXLrUJrwNZEzbMAcu8k344OYo+wfSVygcgZ9lgBdGIzH/nrg3LYhXceynyvTc8t5/GD4Ri0/ng==",
        "dependencies": {
          "System.Reflection": "4.3.0",
          "System.Reflection.Primitives": "4.3.0",
          "System.Runtime": "4.3.0"
        }
      },
      "System.Reflection.Emit.Lightweight": {
        "type": "Transitive",
        "resolved": "4.3.0",
        "contentHash": "oadVHGSMsTmZsAF864QYN1t1QzZjIcuKU3l2S9cZOwDdDueNTrqq1yRj7koFfIGEnKpt6NjpL3rOzRhs4ryOgA==",
        "dependencies": {
          "System.Reflection": "4.3.0",
          "System.Reflection.Emit.ILGeneration": "4.3.0",
          "System.Reflection.Primitives": "4.3.0",
          "System.Runtime": "4.3.0"
        }
      },
      "System.Reflection.Extensions": {
        "type": "Transitive",
        "resolved": "4.3.0",
        "contentHash": "rJkrJD3kBI5B712aRu4DpSIiHRtr6QlfZSQsb0hYHrDCZORXCFjQfoipo2LaMUHoT9i1B7j7MnfaEKWDFmFQNQ==",
        "dependencies": {
          "Microsoft.NETCore.Platforms": "1.1.0",
          "Microsoft.NETCore.Targets": "1.1.0",
          "System.Reflection": "4.3.0",
          "System.Runtime": "4.3.0"
        }
      },
      "System.Reflection.Metadata": {
        "type": "Transitive",
        "resolved": "5.0.0",
        "contentHash": "5NecZgXktdGg34rh1OenY1rFNDCI8xSjFr+Z4OU4cU06AQHUdRnIIEeWENu3Wl4YowbzkymAIMvi3WyK9U53pQ=="
      },
      "System.Reflection.Primitives": {
        "type": "Transitive",
        "resolved": "4.3.0",
        "contentHash": "5RXItQz5As4xN2/YUDxdpsEkMhvw3e6aNveFXUn4Hl/udNTCNhnKp8lT9fnc3MhvGKh1baak5CovpuQUXHAlIA==",
        "dependencies": {
          "Microsoft.NETCore.Platforms": "1.1.0",
          "Microsoft.NETCore.Targets": "1.1.0",
          "System.Runtime": "4.3.0"
        }
      },
      "System.Reflection.TypeExtensions": {
        "type": "Transitive",
        "resolved": "4.3.0",
        "contentHash": "7u6ulLcZbyxB5Gq0nMkQttcdBTx57ibzw+4IOXEfR+sXYQoHvjW5LTLyNr8O22UIMrqYbchJQJnos4eooYzYJA==",
        "dependencies": {
          "System.Reflection": "4.3.0",
          "System.Runtime": "4.3.0"
        }
      },
      "System.Resources.ResourceManager": {
        "type": "Transitive",
        "resolved": "4.3.0",
        "contentHash": "/zrcPkkWdZmI4F92gL/TPumP98AVDu/Wxr3CSJGQQ+XN6wbRZcyfSKVoPo17ilb3iOr0cCRqJInGwNMolqhS8A==",
        "dependencies": {
          "Microsoft.NETCore.Platforms": "1.1.0",
          "Microsoft.NETCore.Targets": "1.1.0",
          "System.Globalization": "4.3.0",
          "System.Reflection": "4.3.0",
          "System.Runtime": "4.3.0"
        }
      },
      "System.Runtime": {
        "type": "Transitive",
        "resolved": "4.3.0",
        "contentHash": "JufQi0vPQ0xGnAczR13AUFglDyVYt4Kqnz1AZaiKZ5+GICq0/1MH/mO/eAJHt/mHW1zjKBJd7kV26SrxddAhiw==",
        "dependencies": {
          "Microsoft.NETCore.Platforms": "1.1.0",
          "Microsoft.NETCore.Targets": "1.1.0"
        }
      },
      "System.Runtime.CompilerServices.Unsafe": {
        "type": "Transitive",
        "resolved": "6.0.0",
        "contentHash": "/iUeP3tq1S0XdNNoMz5C9twLSrM/TH+qElHkXWaPvuNOt+99G75NrV0OS2EqHx5wMN7popYjpc8oTjC1y16DLg=="
      },
      "System.Runtime.Extensions": {
        "type": "Transitive",
        "resolved": "4.3.0",
        "contentHash": "guW0uK0fn5fcJJ1tJVXYd7/1h5F+pea1r7FLSOz/f8vPEqbR2ZAknuRDvTQ8PzAilDveOxNjSfr0CHfIQfFk8g==",
        "dependencies": {
          "Microsoft.NETCore.Platforms": "1.1.0",
          "Microsoft.NETCore.Targets": "1.1.0",
          "System.Runtime": "4.3.0"
        }
      },
      "System.Runtime.Handles": {
        "type": "Transitive",
        "resolved": "4.3.0",
        "contentHash": "OKiSUN7DmTWeYb3l51A7EYaeNMnvxwE249YtZz7yooT4gOZhmTjIn48KgSsw2k2lYdLgTKNJw/ZIfSElwDRVgg==",
        "dependencies": {
          "Microsoft.NETCore.Platforms": "1.1.0",
          "Microsoft.NETCore.Targets": "1.1.0",
          "System.Runtime": "4.3.0"
        }
      },
      "System.Runtime.InteropServices": {
        "type": "Transitive",
        "resolved": "4.3.0",
        "contentHash": "uv1ynXqiMK8mp1GM3jDqPCFN66eJ5w5XNomaK2XD+TuCroNTLFGeZ+WCmBMcBDyTFKou3P6cR6J/QsaqDp7fGQ==",
        "dependencies": {
          "Microsoft.NETCore.Platforms": "1.1.0",
          "Microsoft.NETCore.Targets": "1.1.0",
          "System.Reflection": "4.3.0",
          "System.Reflection.Primitives": "4.3.0",
          "System.Runtime": "4.3.0",
          "System.Runtime.Handles": "4.3.0"
        }
      },
      "System.Text.Encoding": {
        "type": "Transitive",
        "resolved": "4.3.0",
        "contentHash": "BiIg+KWaSDOITze6jGQynxg64naAPtqGHBwDrLaCtixsa5bKiR8dpPOHA7ge3C0JJQizJE+sfkz1wV+BAKAYZw==",
        "dependencies": {
          "Microsoft.NETCore.Platforms": "1.1.0",
          "Microsoft.NETCore.Targets": "1.1.0",
          "System.Runtime": "4.3.0"
        }
      },
      "System.Text.Encoding.CodePages": {
        "type": "Transitive",
        "resolved": "4.5.1",
        "contentHash": "4J2JQXbftjPMppIHJ7IC+VXQ9XfEagN92vZZNoG12i+zReYlim5dMoXFC1Zzg7tsnKDM7JPo5bYfFK4Jheq44w==",
        "dependencies": {
          "Microsoft.NETCore.Platforms": "2.1.2",
          "System.Runtime.CompilerServices.Unsafe": "4.5.2"
        }
      },
      "System.Text.Encodings.Web": {
        "type": "Transitive",
        "resolved": "7.0.0",
        "contentHash": "OP6umVGxc0Z0MvZQBVigj4/U31Pw72ITihDWP9WiWDm+q5aoe0GaJivsfYGq53o6dxH7DcXWiCTl7+0o2CGdmg=="
      },
      "System.Threading": {
        "type": "Transitive",
        "resolved": "4.3.0",
        "contentHash": "VkUS0kOBcUf3Wwm0TSbrevDDZ6BlM+b/HRiapRFWjM5O0NS0LviG0glKmFK+hhPDd1XFeSdU1GmlLhb2CoVpIw==",
        "dependencies": {
          "System.Runtime": "4.3.0",
          "System.Threading.Tasks": "4.3.0"
        }
      },
      "System.Threading.Tasks": {
        "type": "Transitive",
        "resolved": "4.3.0",
        "contentHash": "LbSxKEdOUhVe8BezB/9uOGGppt+nZf6e1VFyw6v3DN6lqitm0OSn2uXMOdtP0M3W4iMcqcivm2J6UgqiwwnXiA==",
        "dependencies": {
          "Microsoft.NETCore.Platforms": "1.1.0",
          "Microsoft.NETCore.Targets": "1.1.0",
          "System.Runtime": "4.3.0"
        }
      },
      "System.Threading.Tasks.Extensions": {
        "type": "Transitive",
        "resolved": "4.5.4",
        "contentHash": "zteT+G8xuGu6mS+mzDzYXbzS7rd3K6Fjb9RiZlYlJPam2/hU7JCBZBVEcywNuR+oZ1ncTvc/cq0faRr3P01OVg=="
      },
      "Tmds.DBus.Protocol": {
        "type": "Transitive",
        "resolved": "0.15.0",
        "contentHash": "QVo/Y39nTYcCKBqrZuwHjXdwaky0yTQPIT3qUTEEK2MZfDtZWrJ2XyZ59zH8LBgB2fL5cWaTuP2pBTpGz/GeDQ==",
        "dependencies": {
          "System.IO.Pipelines": "6.0.0"
        }
      },
      "Avalonia.Controls.DataGrid": {
        "type": "CentralTransitive",
        "requested": "[0.10.12, )",
        "resolved": "11.0.7",
        "contentHash": "RpqeW/nn6btV+TWiFiGizIU/Z4Tj+ALD/TkOtmv/ryJ9EmBSN9S4fED3Unck7I/339NaxeImIO5hhENAQgrW1A==",
        "dependencies": {
          "Avalonia": "11.0.7",
          "Avalonia.Remote.Protocol": "11.0.7"
        }
      },
      "System.IO.Pipelines": {
        "type": "CentralTransitive",
        "requested": "[6.0.1, )",
        "resolved": "6.0.0",
        "contentHash": "mXX66shZ4xLlI3vNLaJ0lt8OIZdmXTvIqXRdQX5HLVGSkLhINLsVhyZuX2UdRFnOGkqnwmMUs40pIIQ7mna4+A=="
      }
    },
    "net8.0/linux-x64": {
      "Avalonia.Angle.Windows.Natives": {
        "type": "Transitive",
        "resolved": "2.1.0.2023020321",
        "contentHash": "Zlkkb8ipxrxNWVPCJgMO19fpcpYPP+bpOQ+jPtCFj8v+TzVvPdnGHuyv9IMvSHhhMfEpps4m4hjaP4FORQYVAA=="
      },
      "Avalonia.Native": {
        "type": "Transitive",
        "resolved": "11.0.7",
        "contentHash": "STdM/t3phThu+kigdoPLrivVDyYxc7lxpIwjlptzZ/0PhMxno/tKqDklatu/g4au9r+NsfQJEHctghLL1dvrSQ==",
        "dependencies": {
          "Avalonia": "11.0.7"
        }
      },
      "HarfBuzzSharp.NativeAssets.Linux": {
        "type": "Transitive",
        "resolved": "7.3.0",
        "contentHash": "m6F2pEBTN0zTRgQ3caJQRGQkZZizZwHHCbu+rTv+gvwteNBOpqOLD5GE4dB9TFjNNpnyHXtfuMD86JuUra9UvA==",
        "dependencies": {
          "HarfBuzzSharp": "7.3.0"
        }
      },
      "HarfBuzzSharp.NativeAssets.macOS": {
        "type": "Transitive",
        "resolved": "7.3.0",
        "contentHash": "LWcFJ39j+dN0KK8c/GJJZPPZPL9TqT2FA42/LRGqzUMmSm5LYbINOMnPvUr7RuLR6RFSmKIrgrlgObR8G5ho2A=="
      },
      "HarfBuzzSharp.NativeAssets.Win32": {
        "type": "Transitive",
        "resolved": "7.3.0",
        "contentHash": "ulEewLMk+dNmbmpy15ny/YusI6JNUWqchF080TV2jgfFBXPXjWm767JleDi/S7hp8eDeEN6GYIIxpvNr5fLvIw=="
      },
      "Microsoft.Win32.SystemEvents": {
        "type": "Transitive",
        "resolved": "6.0.0",
        "contentHash": "hqTM5628jSsQiv+HGpiq3WKBl2c8v1KZfby2J6Pr7pEPlK9waPdgEO6b8A/+/xn/yZ9ulv8HuqK71ONy2tg67A=="
      },
      "runtime.any.System.Collections": {
        "type": "Transitive",
        "resolved": "4.3.0",
        "contentHash": "23g6rqftKmovn2cLeGsuHUYm0FD7pdutb0uQMJpZ3qTvq+zHkgmt6J65VtRry4WDGYlmkMa4xDACtaQ94alNag==",
        "dependencies": {
          "System.Runtime": "4.3.0"
        }
      },
      "runtime.any.System.Globalization": {
        "type": "Transitive",
        "resolved": "4.3.0",
        "contentHash": "sMDBnad4rp4t7GY442Jux0MCUuKL4otn5BK6Ni0ARTXTSpRNBzZ7hpMfKSvnVSED5kYJm96YOWsqV0JH0d2uuw=="
      },
      "runtime.any.System.IO": {
        "type": "Transitive",
        "resolved": "4.3.0",
        "contentHash": "SDZ5AD1DtyRoxYtEcqQ3HDlcrorMYXZeCt7ZhG9US9I5Vva+gpIWDGMkcwa5XiKL0ceQKRZIX2x0XEjLX7PDzQ=="
      },
      "runtime.any.System.Reflection": {
        "type": "Transitive",
        "resolved": "4.3.0",
        "contentHash": "hLC3A3rI8jipR5d9k7+f0MgRCW6texsAp0MWkN/ci18FMtQ9KH7E2vDn/DH2LkxsszlpJpOn9qy6Z6/69rH6eQ=="
      },
      "runtime.any.System.Reflection.Extensions": {
        "type": "Transitive",
        "resolved": "4.3.0",
        "contentHash": "cPhT+Vqu52+cQQrDai/V91gubXUnDKNRvlBnH+hOgtGyHdC17aQIU64EaehwAQymd7kJA5rSrVRNfDYrbhnzyA=="
      },
      "runtime.any.System.Reflection.Primitives": {
        "type": "Transitive",
        "resolved": "4.3.0",
        "contentHash": "Nrm1p3armp6TTf2xuvaa+jGTTmncALWFq22CpmwRvhDf6dE9ZmH40EbOswD4GnFLrMRS0Ki6Kx5aUPmKK/hZBg=="
      },
      "runtime.any.System.Resources.ResourceManager": {
        "type": "Transitive",
        "resolved": "4.3.0",
        "contentHash": "Lxb89SMvf8w9p9+keBLyL6H6x/TEmc6QVsIIA0T36IuyOY3kNvIdyGddA2qt35cRamzxF8K5p0Opq4G4HjNbhQ=="
      },
      "runtime.any.System.Runtime": {
        "type": "Transitive",
        "resolved": "4.3.0",
        "contentHash": "fRS7zJgaG9NkifaAxGGclDDoRn9HC7hXACl52Or06a/fxdzDajWb5wov3c6a+gVSlekRoexfjwQSK9sh5um5LQ==",
        "dependencies": {
          "System.Private.Uri": "4.3.0"
        }
      },
      "runtime.any.System.Runtime.Handles": {
        "type": "Transitive",
        "resolved": "4.3.0",
        "contentHash": "GG84X6vufoEzqx8PbeBKheE4srOhimv+yLtGb/JkR3Y2FmoqmueLNFU4Xx8Y67plFpltQSdK74x0qlEhIpv/CQ=="
      },
      "runtime.any.System.Runtime.InteropServices": {
        "type": "Transitive",
        "resolved": "4.3.0",
        "contentHash": "lBoFeQfxe/4eqjPi46E0LU/YaCMdNkQ8B4MZu/mkzdIAZh8RQ1NYZSj0egrQKdgdvlPFtP4STtob40r4o2DBAw=="
      },
      "runtime.any.System.Text.Encoding": {
        "type": "Transitive",
        "resolved": "4.3.0",
        "contentHash": "+ihI5VaXFCMVPJNstG4O4eo1CfbrByLxRrQQTqOTp1ttK0kUKDqOdBSTaCB2IBk/QtjDrs6+x4xuezyMXdm0HQ=="
      },
      "runtime.any.System.Threading.Tasks": {
        "type": "Transitive",
        "resolved": "4.3.0",
        "contentHash": "OhBAVBQG5kFj1S+hCEQ3TUHBAEtZ3fbEMgZMRNdN8A0Pj4x+5nTELEqL59DU0TjKVE6II3dqKw4Dklb3szT65w=="
      },
      "runtime.debian.8-x64.runtime.native.System.Security.Cryptography.OpenSsl": {
        "type": "Transitive",
        "resolved": "4.3.0",
        "contentHash": "HdSSp5MnJSsg08KMfZThpuLPJpPwE5hBXvHwoKWosyHHfe8Mh5WKT0ylEOf6yNzX6Ngjxe4Whkafh5q7Ymac4Q=="
      },
      "runtime.fedora.23-x64.runtime.native.System.Security.Cryptography.OpenSsl": {
        "type": "Transitive",
        "resolved": "4.3.0",
        "contentHash": "+yH1a49wJMy8Zt4yx5RhJrxO/DBDByAiCzNwiETI+1S4mPdCu0OY4djdciC7Vssk0l22wQaDLrXxXkp+3+7bVA=="
      },
      "runtime.fedora.24-x64.runtime.native.System.Security.Cryptography.OpenSsl": {
        "type": "Transitive",
        "resolved": "4.3.0",
        "contentHash": "c3YNH1GQJbfIPJeCnr4avseugSqPrxwIqzthYyZDN6EuOyNOzq+y2KSUfRcXauya1sF4foESTgwM5e1A8arAKw=="
      },
      "runtime.native.System": {
        "type": "Transitive",
        "resolved": "4.3.0",
        "contentHash": "c/qWt2LieNZIj1jGnVNsE2Kl23Ya2aSTBuXMD6V7k9KWr6l16Tqdwq+hJScEpWER9753NWC8h96PaVNY5Ld7Jw==",
        "dependencies": {
          "Microsoft.NETCore.Platforms": "1.1.0",
          "Microsoft.NETCore.Targets": "1.1.0"
        }
      },
      "runtime.native.System.Security.Cryptography.OpenSsl": {
        "type": "Transitive",
        "resolved": "4.3.0",
        "contentHash": "NS1U+700m4KFRHR5o4vo9DSlTmlCKu/u7dtE5sUHVIPB+xpXxYQvgBgA6wEIeCz6Yfn0Z52/72WYsToCEPJnrw==",
        "dependencies": {
          "runtime.debian.8-x64.runtime.native.System.Security.Cryptography.OpenSsl": "4.3.0",
          "runtime.fedora.23-x64.runtime.native.System.Security.Cryptography.OpenSsl": "4.3.0",
          "runtime.fedora.24-x64.runtime.native.System.Security.Cryptography.OpenSsl": "4.3.0",
          "runtime.opensuse.13.2-x64.runtime.native.System.Security.Cryptography.OpenSsl": "4.3.0",
          "runtime.opensuse.42.1-x64.runtime.native.System.Security.Cryptography.OpenSsl": "4.3.0",
          "runtime.osx.10.10-x64.runtime.native.System.Security.Cryptography.OpenSsl": "4.3.0",
          "runtime.rhel.7-x64.runtime.native.System.Security.Cryptography.OpenSsl": "4.3.0",
          "runtime.ubuntu.14.04-x64.runtime.native.System.Security.Cryptography.OpenSsl": "4.3.0",
          "runtime.ubuntu.16.04-x64.runtime.native.System.Security.Cryptography.OpenSsl": "4.3.0",
          "runtime.ubuntu.16.10-x64.runtime.native.System.Security.Cryptography.OpenSsl": "4.3.0"
        }
      },
      "runtime.opensuse.13.2-x64.runtime.native.System.Security.Cryptography.OpenSsl": {
        "type": "Transitive",
        "resolved": "4.3.0",
        "contentHash": "b3pthNgxxFcD+Pc0WSEoC0+md3MyhRS6aCEeenvNE3Fdw1HyJ18ZhRFVJJzIeR/O/jpxPboB805Ho0T3Ul7w8A=="
      },
      "runtime.opensuse.42.1-x64.runtime.native.System.Security.Cryptography.OpenSsl": {
        "type": "Transitive",
        "resolved": "4.3.0",
        "contentHash": "KeLz4HClKf+nFS7p/6Fi/CqyLXh81FpiGzcmuS8DGi9lUqSnZ6Es23/gv2O+1XVGfrbNmviF7CckBpavkBoIFQ=="
      },
      "runtime.osx.10.10-x64.runtime.native.System.Security.Cryptography.OpenSsl": {
        "type": "Transitive",
        "resolved": "4.3.0",
        "contentHash": "X7IdhILzr4ROXd8mI1BUCQMSHSQwelUlBjF1JyTKCjXaOGn2fB4EKBxQbCK2VjO3WaWIdlXZL3W6TiIVnrhX4g=="
      },
      "runtime.rhel.7-x64.runtime.native.System.Security.Cryptography.OpenSsl": {
        "type": "Transitive",
        "resolved": "4.3.0",
        "contentHash": "nyFNiCk/r+VOiIqreLix8yN+q3Wga9+SE8BCgkf+2BwEKiNx6DyvFjCgkfV743/grxv8jHJ8gUK4XEQw7yzRYg=="
      },
      "runtime.ubuntu.14.04-x64.runtime.native.System.Security.Cryptography.OpenSsl": {
        "type": "Transitive",
        "resolved": "4.3.0",
        "contentHash": "ytoewC6wGorL7KoCAvRfsgoJPJbNq+64k2SqW6JcOAebWsFUvCCYgfzQMrnpvPiEl4OrblUlhF2ji+Q1+SVLrQ=="
      },
      "runtime.ubuntu.16.04-x64.runtime.native.System.Security.Cryptography.OpenSsl": {
        "type": "Transitive",
        "resolved": "4.3.0",
        "contentHash": "I8bKw2I8k58Wx7fMKQJn2R8lamboCAiHfHeV/pS65ScKWMMI0+wJkLYlEKvgW1D/XvSl/221clBoR2q9QNNM7A=="
      },
      "runtime.ubuntu.16.10-x64.runtime.native.System.Security.Cryptography.OpenSsl": {
        "type": "Transitive",
        "resolved": "4.3.0",
        "contentHash": "VB5cn/7OzUfzdnC8tqAIMQciVLiq2epm2NrAm1E9OjNRyG4lVhfR61SMcLizejzQP8R8Uf/0l5qOIbUEi+RdEg=="
      },
      "runtime.unix.System.Diagnostics.Debug": {
        "type": "Transitive",
        "resolved": "4.3.0",
        "contentHash": "WV8KLRHWVUVUDduFnvGMHt0FsEt2wK6xPl1EgDKlaMx2KnZ43A/O0GzP8wIuvAC7mq4T9V1mm90r+PXkL9FPdQ==",
        "dependencies": {
          "runtime.native.System": "4.3.0"
        }
      },
      "runtime.unix.System.Private.Uri": {
        "type": "Transitive",
        "resolved": "4.3.0",
        "contentHash": "ooWzobr5RAq34r9uan1r/WPXJYG1XWy9KanrxNvEnBzbFdQbMG7Y3bVi4QxR7xZMNLOxLLTAyXvnSkfj5boZSg==",
        "dependencies": {
          "runtime.native.System": "4.3.0"
        }
      },
      "runtime.unix.System.Runtime.Extensions": {
        "type": "Transitive",
        "resolved": "4.3.0",
        "contentHash": "zQiTBVpiLftTQZW8GFsV0gjYikB1WMkEPIxF5O6RkUrSV/OgvRRTYgeFQha/0keBpuS0HYweraGRwhfhJ7dj7w==",
        "dependencies": {
          "System.Private.Uri": "4.3.0",
          "runtime.native.System": "4.3.0",
          "runtime.native.System.Security.Cryptography.OpenSsl": "4.3.0"
        }
      },
      "SkiaSharp.NativeAssets.Linux": {
        "type": "Transitive",
        "resolved": "2.88.7",
        "contentHash": "i9VitS7/5D8Te3B1Gu7F6kakW9PYVnI3YC6MoR6NidreD9hDl1EIOQEBaa0eBsOsWNX5Bz92OVf6+7KbDrJvyg==",
        "dependencies": {
          "SkiaSharp": "2.88.7"
        }
      },
      "SkiaSharp.NativeAssets.macOS": {
        "type": "Transitive",
        "resolved": "2.88.7",
        "contentHash": "3jNzco4VjcYPFNxR9aNWcgweFXbTSdM1VpNRzCS4X0i1A1OuNqcaulrAvmntNpujeWxHo9e6WGh6FN8Jf5+XhA=="
      },
      "SkiaSharp.NativeAssets.Win32": {
        "type": "Transitive",
        "resolved": "2.88.7",
        "contentHash": "BCXmWdQ0oVck9vRwC8U3ocSaTHEx28VB+6qw9OxGIMQ86iO5bp4Flqk3IXH0l9Pbr7vWAUOpI212iaL9mTaUZQ=="
      },
      "System.Collections": {
        "type": "Transitive",
        "resolved": "4.3.0",
        "contentHash": "3Dcj85/TBdVpL5Zr+gEEBUuFe2icOnLalmEh9hfck1PTYbbyWuZgh4fmm2ysCLTrqLQw6t3TgTyJ+VLp+Qb+Lw==",
        "dependencies": {
          "Microsoft.NETCore.Platforms": "1.1.0",
          "Microsoft.NETCore.Targets": "1.1.0",
          "System.Runtime": "4.3.0",
          "runtime.any.System.Collections": "4.3.0"
        }
      },
      "System.Diagnostics.Debug": {
        "type": "Transitive",
        "resolved": "4.3.0",
        "contentHash": "ZUhUOdqmaG5Jk3Xdb8xi5kIyQYAA4PnTNlHx1mu9ZY3qv4ELIdKbnL/akbGaKi2RnNUWaZsAs31rvzFdewTj2g==",
        "dependencies": {
          "Microsoft.NETCore.Platforms": "1.1.0",
          "Microsoft.NETCore.Targets": "1.1.0",
          "System.Runtime": "4.3.0",
          "runtime.unix.System.Diagnostics.Debug": "4.3.0"
        }
      },
      "System.Drawing.Common": {
        "type": "Transitive",
        "resolved": "6.0.0",
        "contentHash": "NfuoKUiP2nUWwKZN6twGqXioIe1zVD0RIj2t976A+czLHr2nY454RwwXs6JU9Htc6mwqL6Dn/nEL3dpVf2jOhg==",
        "dependencies": {
          "Microsoft.Win32.SystemEvents": "6.0.0"
        }
      },
      "System.Globalization": {
        "type": "Transitive",
        "resolved": "4.3.0",
        "contentHash": "kYdVd2f2PAdFGblzFswE4hkNANJBKRmsfa2X5LG2AcWE1c7/4t0pYae1L8vfZ5xvE2nK/R9JprtToA61OSHWIg==",
        "dependencies": {
          "Microsoft.NETCore.Platforms": "1.1.0",
          "Microsoft.NETCore.Targets": "1.1.0",
          "System.Runtime": "4.3.0",
          "runtime.any.System.Globalization": "4.3.0"
        }
      },
      "System.IO": {
        "type": "Transitive",
        "resolved": "4.3.0",
        "contentHash": "3qjaHvxQPDpSOYICjUoTsmoq5u6QJAFRUITgeT/4gqkF1bajbSmb1kwSxEA8AHlofqgcKJcM8udgieRNhaJ5Cg==",
        "dependencies": {
          "Microsoft.NETCore.Platforms": "1.1.0",
          "Microsoft.NETCore.Targets": "1.1.0",
          "System.Runtime": "4.3.0",
          "System.Text.Encoding": "4.3.0",
          "System.Threading.Tasks": "4.3.0",
          "runtime.any.System.IO": "4.3.0"
        }
      },
      "System.Private.Uri": {
        "type": "Transitive",
        "resolved": "4.3.0",
        "contentHash": "I4SwANiUGho1esj4V4oSlPllXjzCZDE+5XXso2P03LW2vOda2Enzh8DWOxwN6hnrJyp314c7KuVu31QYhRzOGg==",
        "dependencies": {
          "Microsoft.NETCore.Platforms": "1.1.0",
          "Microsoft.NETCore.Targets": "1.1.0",
          "runtime.unix.System.Private.Uri": "4.3.0"
        }
      },
      "System.Reflection": {
        "type": "Transitive",
        "resolved": "4.3.0",
        "contentHash": "KMiAFoW7MfJGa9nDFNcfu+FpEdiHpWgTcS2HdMpDvt9saK3y/G4GwprPyzqjFH9NTaGPQeWNHU+iDlDILj96aQ==",
        "dependencies": {
          "Microsoft.NETCore.Platforms": "1.1.0",
          "Microsoft.NETCore.Targets": "1.1.0",
          "System.IO": "4.3.0",
          "System.Reflection.Primitives": "4.3.0",
          "System.Runtime": "4.3.0",
          "runtime.any.System.Reflection": "4.3.0"
        }
      },
      "System.Reflection.Extensions": {
        "type": "Transitive",
        "resolved": "4.3.0",
        "contentHash": "rJkrJD3kBI5B712aRu4DpSIiHRtr6QlfZSQsb0hYHrDCZORXCFjQfoipo2LaMUHoT9i1B7j7MnfaEKWDFmFQNQ==",
        "dependencies": {
          "Microsoft.NETCore.Platforms": "1.1.0",
          "Microsoft.NETCore.Targets": "1.1.0",
          "System.Reflection": "4.3.0",
          "System.Runtime": "4.3.0",
          "runtime.any.System.Reflection.Extensions": "4.3.0"
        }
      },
      "System.Reflection.Primitives": {
        "type": "Transitive",
        "resolved": "4.3.0",
        "contentHash": "5RXItQz5As4xN2/YUDxdpsEkMhvw3e6aNveFXUn4Hl/udNTCNhnKp8lT9fnc3MhvGKh1baak5CovpuQUXHAlIA==",
        "dependencies": {
          "Microsoft.NETCore.Platforms": "1.1.0",
          "Microsoft.NETCore.Targets": "1.1.0",
          "System.Runtime": "4.3.0",
          "runtime.any.System.Reflection.Primitives": "4.3.0"
        }
      },
      "System.Resources.ResourceManager": {
        "type": "Transitive",
        "resolved": "4.3.0",
        "contentHash": "/zrcPkkWdZmI4F92gL/TPumP98AVDu/Wxr3CSJGQQ+XN6wbRZcyfSKVoPo17ilb3iOr0cCRqJInGwNMolqhS8A==",
        "dependencies": {
          "Microsoft.NETCore.Platforms": "1.1.0",
          "Microsoft.NETCore.Targets": "1.1.0",
          "System.Globalization": "4.3.0",
          "System.Reflection": "4.3.0",
          "System.Runtime": "4.3.0",
          "runtime.any.System.Resources.ResourceManager": "4.3.0"
        }
      },
      "System.Runtime": {
        "type": "Transitive",
        "resolved": "4.3.0",
        "contentHash": "JufQi0vPQ0xGnAczR13AUFglDyVYt4Kqnz1AZaiKZ5+GICq0/1MH/mO/eAJHt/mHW1zjKBJd7kV26SrxddAhiw==",
        "dependencies": {
          "Microsoft.NETCore.Platforms": "1.1.0",
          "Microsoft.NETCore.Targets": "1.1.0",
          "runtime.any.System.Runtime": "4.3.0"
        }
      },
      "System.Runtime.Extensions": {
        "type": "Transitive",
        "resolved": "4.3.0",
        "contentHash": "guW0uK0fn5fcJJ1tJVXYd7/1h5F+pea1r7FLSOz/f8vPEqbR2ZAknuRDvTQ8PzAilDveOxNjSfr0CHfIQfFk8g==",
        "dependencies": {
          "Microsoft.NETCore.Platforms": "1.1.0",
          "Microsoft.NETCore.Targets": "1.1.0",
          "System.Runtime": "4.3.0",
          "runtime.unix.System.Runtime.Extensions": "4.3.0"
        }
      },
      "System.Runtime.Handles": {
        "type": "Transitive",
        "resolved": "4.3.0",
        "contentHash": "OKiSUN7DmTWeYb3l51A7EYaeNMnvxwE249YtZz7yooT4gOZhmTjIn48KgSsw2k2lYdLgTKNJw/ZIfSElwDRVgg==",
        "dependencies": {
          "Microsoft.NETCore.Platforms": "1.1.0",
          "Microsoft.NETCore.Targets": "1.1.0",
          "System.Runtime": "4.3.0",
          "runtime.any.System.Runtime.Handles": "4.3.0"
        }
      },
      "System.Runtime.InteropServices": {
        "type": "Transitive",
        "resolved": "4.3.0",
        "contentHash": "uv1ynXqiMK8mp1GM3jDqPCFN66eJ5w5XNomaK2XD+TuCroNTLFGeZ+WCmBMcBDyTFKou3P6cR6J/QsaqDp7fGQ==",
        "dependencies": {
          "Microsoft.NETCore.Platforms": "1.1.0",
          "Microsoft.NETCore.Targets": "1.1.0",
          "System.Reflection": "4.3.0",
          "System.Reflection.Primitives": "4.3.0",
          "System.Runtime": "4.3.0",
          "System.Runtime.Handles": "4.3.0",
          "runtime.any.System.Runtime.InteropServices": "4.3.0"
        }
      },
      "System.Text.Encoding": {
        "type": "Transitive",
        "resolved": "4.3.0",
        "contentHash": "BiIg+KWaSDOITze6jGQynxg64naAPtqGHBwDrLaCtixsa5bKiR8dpPOHA7ge3C0JJQizJE+sfkz1wV+BAKAYZw==",
        "dependencies": {
          "Microsoft.NETCore.Platforms": "1.1.0",
          "Microsoft.NETCore.Targets": "1.1.0",
          "System.Runtime": "4.3.0",
          "runtime.any.System.Text.Encoding": "4.3.0"
        }
      },
      "System.Text.Encoding.CodePages": {
        "type": "Transitive",
        "resolved": "4.5.1",
        "contentHash": "4J2JQXbftjPMppIHJ7IC+VXQ9XfEagN92vZZNoG12i+zReYlim5dMoXFC1Zzg7tsnKDM7JPo5bYfFK4Jheq44w==",
        "dependencies": {
          "Microsoft.NETCore.Platforms": "2.1.2",
          "System.Runtime.CompilerServices.Unsafe": "4.5.2"
        }
      },
      "System.Text.Encodings.Web": {
        "type": "Transitive",
        "resolved": "7.0.0",
        "contentHash": "OP6umVGxc0Z0MvZQBVigj4/U31Pw72ITihDWP9WiWDm+q5aoe0GaJivsfYGq53o6dxH7DcXWiCTl7+0o2CGdmg=="
      },
      "System.Threading.Tasks": {
        "type": "Transitive",
        "resolved": "4.3.0",
        "contentHash": "LbSxKEdOUhVe8BezB/9uOGGppt+nZf6e1VFyw6v3DN6lqitm0OSn2uXMOdtP0M3W4iMcqcivm2J6UgqiwwnXiA==",
        "dependencies": {
          "Microsoft.NETCore.Platforms": "1.1.0",
          "Microsoft.NETCore.Targets": "1.1.0",
          "System.Runtime": "4.3.0",
          "runtime.any.System.Threading.Tasks": "4.3.0"
        }
      }
    }
  }
}